bamnet/__init__.py
bamnet/bam.py
bamnet-0.1.0.dist-info/METADATA
bamnet-0.1.0.dist-info/WHEEL
bamnet-0.1.0.dist-info/top_level.txt
bamnet-0.1.0.dist-info/RECORD
